{
  "type": "minecraft:crafting_shaped",
  "key": {
    "F": {
      "item": "minecraft:oxeye_daisy"
    },
    "L": {
      "item": "minecraft:leather"
    },
    "V": {
      "item": "minecraft:vine"
    }
  },
  "pattern": [
    "FVF",
    "FLF",
    "FVF"
  ],
  "result": {
    "item": "l2world:medicine_leather",
    "nbt": "{CustomPotionEffects:[{Ambient:0b,Amplifier:1b,CurativeItems:[{Count:1b,id:\"minecraft:milk_bucket\"}],Duration:200,Id:10,ShowIcon:1b,ShowParticles:1b,\"forge:id\":\"minecraft:regeneration\"}]}"
  }
}